README.md
setup.py
nginx/example.config
src/bismuth.egg-info/PKG-INFO
src/bismuth.egg-info/SOURCES.txt
src/bismuth.egg-info/dependency_links.txt
src/bismuth.egg-info/entry_points.txt
src/bismuth.egg-info/requires.txt
src/bismuth.egg-info/top_level.txt
src/bismuth_jsclient/app.html
src/bismuth_jsclient/static/client.js
src/bismuth_jsclient/static/style.css
src/bismuth_messages/__init__.py
src/bismuth_messages/outer.py
src/bismuth_messages/proto/__init__.py
src/bismuth_messages/proto/bismuth_message.proto
src/bismuth_messages/proto/bismuth_message_pb2.py
src/bismuth_messages/proto/hash_type.proto
src/bismuth_messages/proto/hash_type_pb2.py
src/bismuth_messages/proto/client_server/__init__.py
src/bismuth_messages/proto/client_server/client_requests.proto
src/bismuth_messages/proto/client_server/client_requests_pb2.py
src/bismuth_messages/proto/client_server/server_responses.proto
src/bismuth_messages/proto/client_server/server_responses_pb2.py
src/bismuth_server/__init__.py
src/bismuth_server/crypto.py
src/bismuth_server/db.py
src/bismuth_server/db_setup.py
src/bismuth_server/hotpatch.py
src/bismuth_server/lru.py
src/bismuth_server/premade.py
src/bismuth_server/server.py
src/bismuth_server/postgres/1_schema_types.sql
src/bismuth_server/postgres/2_schema.sql
test/test_lru.py
test/test_nacl.py
test/test_pg_schema.py
test/postgres/test_errs.sql
test/postgres/test_schema.sql